simo_nuki/__init__.py
simo_nuki/admin.py
simo_nuki/auto_urls.py
simo_nuki/controllers.py
simo_nuki/forms.py
simo_nuki/gateways.py
simo_nuki/models.py
simo_nuki/tasks.py
simo_nuki/views.py
simo_nuki/migrations/0001_initial.py
simo_nuki/migrations/0002_nukibridge_token.py
simo_nuki/migrations/0003_auto_20231006_1351.py
simo_nuki/migrations/0004_auto_20231006_1400.py
simo_nuki/migrations/0005_auto_20231006_1420.py
simo_nuki/migrations/0006_auto_20231011_0823.py
simo_nuki/migrations/__init__.py
simo_nuki-1.0.1.dist-info/LICENSE.md
simo_nuki-1.0.1.dist-info/METADATA
simo_nuki-1.0.1.dist-info/WHEEL
simo_nuki-1.0.1.dist-info/top_level.txt
simo_nuki-1.0.1.dist-info/RECORD
