Metadata-Version: 2.1
Name: simo-nuki
Version: 1.0.1
Summary: Nuki integration for SIMO.io
Author-email: Simanas Venčkauskas <simanas@simo.io>
Project-URL: Homepage, https://github.com/SIMO-io/simo-nuki
Project-URL: Issues, https://github.com/SIMO-io/simo-nuki/issues
Classifier: Programming Language :: Python :: 3
Classifier: License :: OSI Approved :: MIT License
Classifier: Operating System :: OS Independent
Requires-Python: >=3.8
License-File: LICENSE.md
Requires-Dist: simo >=1.5.9
